lkmlstyle/__init__.py
lkmlstyle/check.py
lkmlstyle/cli.py
lkmlstyle/exceptions.py
lkmlstyle/rules.py
lkmlstyle/types.py
lkmlstyle/utils.py
lkmlstyle-0.0.9.dist-info/METADATA
lkmlstyle-0.0.9.dist-info/WHEEL
lkmlstyle-0.0.9.dist-info/entry_points.txt
lkmlstyle-0.0.9.dist-info/top_level.txt
lkmlstyle-0.0.9.dist-info/RECORD
