Metadata-Version: 2.1
Name: lkmlstyle
Version: 0.0.9
Home-page: https://github.com/spectacles-ci/lkmlstyle
Author: Josh Temple
Requires-Python: >=3.10
Requires-Dist: lkml (>=1.3.0b5)
Requires-Dist: rich
Requires-Dist: PyYAML
